mytestapp/__init__.py
mytestapp/mytestapp.py
mytestapp-1.0.0.dist-info/LICENCE
mytestapp-1.0.0.dist-info/METADATA
mytestapp-1.0.0.dist-info/WHEEL
mytestapp-1.0.0.dist-info/entry_points.txt
mytestapp-1.0.0.dist-info/top_level.txt
mytestapp-1.0.0.dist-info/RECORD
